__init__.py
LockonToolAlpha/__init__.py
LockonToolAlpha/_date_param.py
LockonToolAlpha/dflangparserv1.py
LockonToolAlpha/eml_reader.py
LockonToolAlpha/file_tools.py
LockonToolAlpha/logg_conf.py
LockonToolAlpha/time_tools.py
LockonToolAlpha/utools.py
LockonToolAlpha/_trashbin/__init__.py
LockonToolAlpha/_trashbin/dfLangParser.py
LockonToolAlpha-0.0.6.dist-info/LICENSE
LockonToolAlpha-0.0.6.dist-info/METADATA
LockonToolAlpha-0.0.6.dist-info/WHEEL
LockonToolAlpha-0.0.6.dist-info/top_level.txt
LockonToolAlpha-0.0.6.dist-info/RECORD
